crypto/__init__.py
crypto/bitget.py
crypto/gate.py
crypto/grid_strategy.py
crypto/meme.py
crypto/mysql_utils.py
uni_cli/__init__.py
uni_cli/bitget.py
uni_cli/example.py
uni_cli/gate.py
uni_cli/sync.py
uni_cli/util.py
utils/__init__.py
utils/dict.py
utils/draw.py
utils/image.py
utils/mysql.py
utils/ocr.py
utils/pd.py
utils/sleep.py
uni_cli-0.2.8.dist-info/METADATA
uni_cli-0.2.8.dist-info/WHEEL
uni_cli-0.2.8.dist-info/entry_points.txt
uni_cli-0.2.8.dist-info/RECORD
