Metadata-Version: 2.4
Name: uni-cli
Version: 0.2.8
Summary: uni cli
License: MIT License
Keywords: cli,typer
Requires-Python: >=3.10
Requires-Dist: arrow>=1.3.0
Requires-Dist: babel>=2.16.0
Requires-Dist: cowsay>=6.1
Requires-Dist: fastapi>=0.115.5
Requires-Dist: httpx>=0.27.2
Requires-Dist: imagehash>=4.3.1
Requires-Dist: numpy<2.0.0
Requires-Dist: paddleocr>=2.9.1
Requires-Dist: pandas>=2.2.3
Requires-Dist: pillow>=11.0.0
Requires-Dist: pymysql>=1.1.1
Requires-Dist: pytesseract>=0.3.13
Requires-Dist: python-dotenv>=1.0.1
Requires-Dist: pytz>=2024.2
Requires-Dist: requests-toolbelt>=1.0.0
Requires-Dist: requests[socks]>=2.32.3
Requires-Dist: setuptools>=75.2.0
Requires-Dist: sqlalchemy>=2.0.35
Requires-Dist: typer>=0.12.5
Requires-Dist: uvicorn>=0.32.0
